Workbook

Sheet Cria
A1: ENGORDE DE TERNEROS HOLANDO (Etapa crianza)
A3: N° Animales | C3: 100 | G3: $/Ternero | H3: $ Totales
A4: Peso Entrada | C4: 40 | E4: Ingreso | G4: =C5*C11*(1-C12) -> 294400 | H4: =+G4*$C$3 -> 29440000
A5: Peso Salida | C5: 80 | E5: Gastos Comida | G5: =-F20*C8 -> -148579.02 | H5: =+G5*$C$3 -> -14857902
A6: Peso Promedio | C6: =(C5+C4)/2 -> 60 | E6: Gastos Hacienda | G6: =-C4*C10 -> -100000 | H6: =+G6*$C$3 -> -10000000 | J6: 39859 | K6: 95
A7: Ganancia Diaria | C7: =+D7/20 -> 0.65 | D7: 13 | E7: Reparto Comida | G7: =-H7/C3 -> 0 | J7: 39892 | K7: 122
A8: Dias Encierre | C8: =(C5-C4)/C7 -> 61.538462 | E8: Personal | G8: =H8/C3 -> -12307.692 | H8: =1200000/30/2*C8*-1 -> -1230769.2 | K8: =+(K7-K6)/(J7-J6) -> 0.81818182
A9: Consumo M.S (%PV) | C9: 0.03 | D9: 28 | E9: Sanidad | G9: =+H9/C3 -> -8000 | H9: =-8000*C3 -> -800000
A10: Precio Neto Entrada | C10: =100000/40 -> 2500 | D10: 2381 | E10: Margen | G10: =SUM(G4:G9) -> 25513.287 | H10: =+G10*$C$3 -> 2551328.7
A11: Precio Neto Salida | C11: 4000 | D11: 15003 | E11: Rentabilidad por período | H11: =H10/(G20+C3*C4*C10)/C8*365 -> 0.60876288
A12: Mortandad | C12: 0.08
A14: Alimento | C14: % | D14: Kg/Día | E14: $/Ton | F14: $/Día | G14: $/Totales | H14: Kg Totales
A15: Leche | B15: 40 | C15: =+B15/100 -> 0.4 | D15: 4 | E15: 500000 | F15: =+D15*E15/1000 -> 2000 | G15: =+F15*$C$8*$C$3 -> 12307692 | H15: =+D15*$C$8*$C$3 -> 24615.385 | I15: 90000 | J15: =18*3000 -> 54000 | K15: =SUM(I15:J15) -> 144000 | L15: Se podría hacer con parte de leche descarte y bajar este costo
A16: Iniciador | B16: 30 | C16: =+B16/100 -> 0.3 | D16: =$C$6*$C$9*C16/0.88 -> 0.61363636 | E16: 470000 | F16: =+D16*E16/1000 -> 288.40909 | G16: =+F16*$C$8*$C$3 -> 1774825.2 | H16: =+D16*$C$8*$C$3 -> 3776.2238
A17: Rollo Alfalfa | B17: 30 | C17: =+B17/100 -> 0.3 | D17: 0.7 | E17: 180000 | F17: =+D17*E17/1000 -> 126 | G17: =+F17*$C$8*$C$3 -> 775384.62 | H17: =+D17*$C$8*$C$3 -> 4307.6923 | I17: 76000 | J17: =65*3000 -> 195000 | K17: =SUM(I17:J17) -> 271000
A18: Urea | D18: =$C$6*$C$9*C18/0.9 -> 0 | F18: =+D18*E18/1000 -> 0 | G18: =+F18*$C$8*$C$3 -> 0 | H18: =+D18*$C$8*$C$3 -> 0
A19: Nucleo Mineral | B19: 0 | C19: =+B19/100 -> 0 | D19: =$C$6*$C$9*C19/0.9 -> 0 | F19: =+D19*E19/1000 -> 0 | G19: =+F19*$C$8*$C$3 -> 0 | H19: =+D19*$C$8*$C$3 -> 0
A20: Total | C20: =SUM(C15:C19) -> 1 | D20: =SUM(D15:D19) -> 5.3136364 | F20: =SUM(F15:F19) -> 2414.4091 | G20: =+F20*$C$8*$C$3 -> 14857902 | H20: =SUM(H15:H19) -> 32699.301 | J20: =SUM(J15:J19) -> 249000
J21: =+J20/D20 -> 46860.565

Sheet Recria
A1: ENGORDE DE TERNEROS HOLANDO (dieta 2)
A3: N° Animales | C3: 100 | G3: $/Ternero | H3: $ Totales
A4: Peso Entrada | C4: =+Cria!C5 -> 80 | E4: Ingreso | G4: =C5*C11*(1-C12) -> 776000 | H4: =+G4*$C$3 -> 77600000
A5: Peso Salida | C5: 200 | E5: Gastos Comida | G5: =-F20*C8 -> -238254.55 | H5: =+G5*$C$3 -> -23825455
A6: Peso Promedio | C6: =(C5+C4)/2 -> 140 | E6: Gastos Hacienda | G6: =-C4*C10 -> -320000 | H6: =+G6*$C$3 -> -32000000 | J6: 39859 | K6: 95
A7: Ganancia Diaria | C7: =+D7/20 -> 0.8 | D7: 16 | E7: Reparto Comida | G7: =-H7/C3 -> 0 | J7: 39892 | K7: 122
A8: Dias Encierre | C8: =(C5-C4)/C7 -> 150 | E8: Personal | G8: =H8/C3 -> -30000 | H8: =1200000/30/2*C8*-1 -> -3000000 | K8: =+(K7-K6)/(J7-J6) -> 0.81818182 | M8: Consolidado
A9: Consumo M.S (%PV) | C9: 0.03 | D9: 28 | E9: Sanidad | G9: =+H9/C3 -> -12500 | H9: =-12500*C3 -> -1250000 | N9: MB | O9: GD | P9: Ingreso | R9: Ingreso | S9: Dias
A10: Precio Neto Entrada | C10: =+Cria!C11 -> 4000 | D10: 186 | E10: Margen | G10: =SUM(G4:G9) -> 175245.45 | H10: =+G10*$C$3 -> 17524545 | L10: =+G4+G5+G6 -> 217745.45 | M10: Crianza | N10: =+Cria!G10 -> 25513.287 | O10: =+SUM(Cria!G5:G9)*-1 -> 268886.71 | P10: =+Cria!G4 -> 294400 | R10: 46113 | S10: =+R11-R10 -> 61.538462
A11: Precio Neto Salida | C11: 4000 | D11: 15553 | E11: Rentabilidad por período | H11: =H10/(G20+C3*C4*C10)/C8*365 -> 0.7638641 | M11: Recría | N11: =+G10 -> 175245.45 | O11: =+SUM(G5:G9)*-1 -> 600754.55 | P11: =+G4 -> 776000 | R11: =+R10+Cria!C8 -> 46174.538 | S11: =+R12-R11 -> 150
A12: Mortandad | C12: 0.03 | M12: Total | N12: =SUM(N10:N11) -> 200758.74 | O12: =SUM(O10:O11) -> 869641.26 | P12: =SUM(P10:P11) -> 1070400 | R12: =+R11+C8 -> 46324.538 | S12: =+S11+S10 -> 211.53846
M13: Total $$ - 250 Terneros 200kg | N13: =+N12*S13 -> 0 | P13: =+P12*S13 -> 0
A14: Alimento | C14: % | D14: Kg/Día | E14: $/Ton | F14: $/Día | G14: $/Totales | H14: Kg Totales | M14: Total USD - 250 Terneros 200kg | N14: =+N13/1550 -> 0
A15: Maíz | B15: 0 | C15: =+B15/100 -> 0 | D15: =$C$6*$C$9*C15/0.88 -> 0 | E15: 250000 | F15: =+D15*E15/1000 -> 0 | G15: =+F15*$C$8*$C$3 -> 0 | H15: =+D15*$C$8*$C$3 -> 0 | I15: 90000 | J15: =18*3000 -> 54000 | K15: =SUM(I15:J15) -> 144000
A16: Balanceado recria | B16: 70 | C16: =+B16/100 -> 0.7 | D16: =$C$6*$C$9*C16/0.88 -> 3.3409091 | E16: 400000 | F16: =+D16*E16/1000 -> 1336.3636 | G16: =+F16*$C$8*$C$3 -> 20045455 | H16: =+D16*$C$8*$C$3 -> 50113.636
A17: Rollo Alfalfa | B17: 30 | C17: =+B17/100 -> 0.3 | D17: =$C$6*$C$9*C17/0.9 -> 1.4 | E17: 180000 | F17: =+D17*E17/1000 -> 252 | G17: =+F17*$C$8*$C$3 -> 3780000 | H17: =+D17*$C$8*$C$3 -> 21000 | I17: 76000 | J17: =65*3000 -> 195000 | K17: =SUM(I17:J17) -> 271000
A18: Urea | C18: 0 | D18: =$C$6*$C$9*C18/0.9 -> 0 | E18: 2000 | F18: =+D18*E18/1000 -> 0 | G18: =+F18*$C$8*$C$3 -> 0 | H18: =+D18*$C$8*$C$3 -> 0
A19: Nucleo Mineral | B19: 0 | C19: =+B19/100 -> 0 | D19: =$C$6*$C$9*C19/0.9 -> 0 | E19: 2000 | F19: =+D19*E19/1000 -> 0 | G19: =+F19*$C$8*$C$3 -> 0 | H19: =+D19*$C$8*$C$3 -> 0
A20: Total | C20: =SUM(C15:C19) -> 1 | D20: =SUM(D15:D19) -> 4.7409091 | F20: =SUM(F15:F19) -> 1588.3636 | G20: =+F20*$C$8*$C$3 -> 23825455 | H20: =SUM(H15:H19) -> 71113.636 | J20: =SUM(J15:J19) -> 249000
H21: =+H20/150 -> 474.09091 | J21: =+J20/D20 -> 52521.572

Sheet Engorde a corral
A1: ENGORDE DE TERNEROS HOLANDO
A3: N° Animales | C3: 100 | G3: $/Ternero | H3: $ Totales
A4: Peso Entrada | C4: =+Recria!C5 -> 200 | E4: Ingreso | G4: =C5*C11*(1-C12) -> 1548120 | H4: =+G4*$C$3 -> 154812000
A5: Peso Salida | C5: 380 | E5: Gastos Comida | G5: =-F20*C8 -> -498272.73 | H5: =+G5*$C$3 -> -49827273
A6: Peso Promedio | C6: =(C5+C4)/2 -> 290 | E6: Gastos Hacienda | G6: =-C4*C10 -> -800000 | H6: =+G6*$C$3 -> -80000000 | J6: 39859 | K6: 95
A7: Ganancia Diaria | C7: =+D7/20 -> 1.1 | D7: 22 | E7: Reparto Comida | G7: =-H7/C3 -> 0 | J7: 39892 | K7: 122
A8: Dias Encierre | C8: =(C5-C4)/C7 -> 163.63636 | E8: Personal | G8: =H8/C3 -> -32727.273 | H8: =1200000/30/2*C8*-1 -> -3272727.3 | K8: =+(K7-K6)/(J7-J6) -> 0.81818182
A9: Consumo M.S (%PV) | C9: 0.03 | D9: 28 | E9: Sanidad | G9: =+H9/C3 -> 8500 | H9: =+C3*8500 -> 850000
A10: Precio Neto Entrada | C10: =+Recria!C11 -> 4000 | D10: 11000 | E10: Margen | G10: =SUM(G4:G9) -> 225620 | H10: =+G10*$C$3 -> 22562000 | L10: =+G4+G5+G6 -> 249847.27 | M10: =+G10+Recria!G10+Cria!G10 -> 426378.74
A11: Precio Neto Salida | C11: 4200 | D11: 33000 | E11: Rentabilidad por período | H11: =H10/(G20+C3*C4*C10)/C8*365 -> 0.38763654
A12: Mortandad | C12: 0.03
A14: Alimento | C14: % | D14: Kg/Día | E14: $/Ton | F14: $/Día | G14: $/Totales | H14: Kg Totales
A15: Balanceado Novillo | B15: 80 | C15: =+B15/100 -> 0.8 | D15: =$C$6*$C$9*C15/0.88 -> 7.9090909 | E15: 340000 | F15: =+D15*E15/1000 -> 2689.0909 | G15: =+F15*$C$8*$C$3 -> 44003306 | H15: =+D15*$C$8*$C$3 -> 129421.49 | I15: 90000 | J15: =18*3000 -> 54000 | K15: =SUM(I15:J15) -> 144000
A16: Rollos Gramineas | B16: 20 | C16: =+B16/100 -> 0.2 | D16: =$C$6*$C$9*C16/0.88 -> 1.9772727 | E16: 180000 | F16: =+D16*E16/1000 -> 355.90909 | G16: =+F16*$C$8*$C$3 -> 5823966.9 | H16: =+D16*$C$8*$C$3 -> 32355.372
B17: 0 | C17: =+B17/100 -> 0 | D17: =$C$6*$C$9*C17/0.9 -> 0 | E17: 0 | F17: =+D17*E17/1000 -> 0 | G17: =+F17*$C$8*$C$3 -> 0 | H17: =+D17*$C$8*$C$3 -> 0 | I17: 76000 | J17: =65*3000 -> 195000 | K17: =SUM(I17:J17) -> 271000
C18: 0 | D18: =$C$6*$C$9*C18/0.9 -> 0 | E18: 0 | F18: =+D18*E18/1000 -> 0 | G18: =+F18*$C$8*$C$3 -> 0 | H18: =+D18*$C$8*$C$3 -> 0
A19: Nucleo | B19: 0 | C19: =+B19/100 -> 0 | D19: =$C$6*$C$9*C19/0.9 -> 0 | E19: 0 | F19: =+D19*E19/1000 -> 0 | G19: =+F19*$C$8*$C$3 -> 0 | H19: =+D19*$C$8*$C$3 -> 0
A20: Total | C20: =SUM(C15:C19) -> 1 | D20: =SUM(D15:D19) -> 9.8863636 | F20: =SUM(F15:F19) -> 3045 | G20: =+F20*$C$8*$C$3 -> 49827273 | H20: =SUM(H15:H19) -> 161776.86 | J20: =SUM(J15:J19) -> 249000
H21: =+H20/150 -> 1078.5124 | J21: =+J20/D20 -> 25186.207

Sheet Terminacion exportacion
A1: ENGORDE DE NOVILLO HOLANDO
A3: N° Animales | C3: 100 | G3: $/Ternero | H3: $ Totales
A4: Peso Entrada | C4: =+Recria!C5 -> 200 | E4: Ingreso | G4: =C5*C11*(1-C12) -> 1955520 | H4: =+G4*$C$3 -> 195552000
A5: Peso Salida | C5: 480 | E5: Gastos Comida | G5: =-F22*C8 -> -844977.27 | H5: =+G5*$C$3 -> -84497727
A6: Peso Promedio | C6: =(C5+C4)/2 -> 340 | E6: Gastos Hacienda | G6: =-C4*C10 -> -800000 | H6: =+G6*$C$3 -> -80000000 | J6: 39859 | K6: 95
A7: Ganancia Diaria | C7: 0.7 | D7: 12 | E7: Reparto Comida | G7: =-H7/C3 -> 0 | J7: 39892 | K7: 122
A8: Dias Encierre | C8: =(C5-C4)/C7 -> 400 | E8: Personal | G8: =H8/C3 -> -80000 | H8: =1200000/30/2*C8*-1 -> -8000000 | K8: =+(K7-K6)/(J7-J6) -> 0.81818182
A9: Consumo M.S (%PV) | C9: 0.03 | D9: 28 | E9: Sanidad | G9: =+H9/C3 -> -5000 | H9: =-5000*C3 -> -500000
A10: Precio Neto Entrada | C10: =+Recria!C11 -> 4000 | D10: 141 | E10: Margen | G10: =SUM(G4:G9) -> 225542.73 | H10: =+G10*$C$3 -> 22554273
A11: Precio Neto Salida | C11: 4200 | D11: 35000 | E11: Rentabilidad por período | H11: =H10/(G22+C3*C4*C10)/C8*365 -> 0.12511282
A12: Mortandad | C12: 0.03
A14: Alimento | C14: % | D14: Kg/Día | E14: $/Ton | F14: $/Día | G14: $/Totales | H14: Kg Totales
A15: Maíz | B15: 0 | C15: 0.25 | D15: =$C$6*$C$9*C15/0.88 -> 2.8977273 | E15: 260000 | F15: =+D15*E15/1000 -> 753.40909 | G15: =+F15*$C$8*$C$3 -> 30136364 | H15: =+D15*$C$8*$C$3 -> 115909.09
A16: Silo Sorgo | B16: 25 | C16: =+B16/100 -> 0.25 | D16: =$C$6*$C$9*C16/0.9 -> 2.8333333 | E16: 180000 | F16: =+D16*E16/1000 -> 510 | G16: =+F16*$C$8*$C$3 -> 20400000 | H16: =+D16*$C$8*$C$3 -> 113333.33 | I16: 76000 | J16: =65*3000 -> 195000 | K16: =SUM(I16:J16) -> 271000
A17: Alfalfa | B17: 65 | C17: =+B17/100 -> 0.65 | D17: =$C$6*$C$9*C17/0.88 -> 7.5340909 | E17: =85*1000 -> 85000 | F17: =+D17*E17/1000 -> 640.39773 | G17: =+F17*$C$8*$C$3 -> 25615909 | H17: =+D17*$C$8*$C$3 -> 301363.64 | I17: 90000 | J17: =18*3000 -> 54000 | K17: =SUM(I17:J17) -> 144000
A18: Rollos Alfalfa | B18: 10 | C18: =+B18/100 -> 0.1 | D18: =$C$6*$C$9*C18/0.88 -> 1.1590909 | E18: 180000 | F18: =+D18*E18/1000 -> 208.63636 | G18: =+F18*$C$8*$C$3 -> 8345454.5 | H18: =+D18*$C$8*$C$3 -> 46363.636
B19: 0 | C19: =+B19/100 -> 0 | D19: =$C$6*$C$9*C19/0.9 -> 0 | E19: 0 | F19: =+D19*E19/1000 -> 0 | G19: =+F19*$C$8*$C$3 -> 0 | H19: =+D19*$C$8*$C$3 -> 0 | I19: 76000 | J19: =65*3000 -> 195000 | K19: =SUM(I19:J19) -> 271000
B20: 0 | C20: =+B20/100 -> 0 | D20: =$C$6*$C$9*C20/0.9 -> 0 | E20: 0 | F20: =+D20*E20/1000 -> 0 | G20: =+F20*$C$8*$C$3 -> 0 | H20: =+D20*$C$8*$C$3 -> 0
B21: 0 | C21: =+B21/100 -> 0 | D21: =$C$6*$C$9*C21/0.9 -> 0 | E21: 0 | F21: =+D21*E21/1000 -> 0 | G21: =+F21*$C$8*$C$3 -> 0 | H21: =+D21*$C$8*$C$3 -> 0
A22: Total | C22: =SUM(C15:C21) -> 1.25 | D22: =SUM(D15:D21) -> 14.424242 | F22: =SUM(F15:F21) -> 2112.4432 | G22: =+F22*$C$8*$C$3 -> 84497727 | H22: =SUM(H15:H21) -> 576969.7 | J22: =SUM(J15:J21) -> 444000
J23: =+J22/D22 -> 30781.513
